.ansible-lint
.gitignore
LICENSE
MANIFEST.in
README.md
pyproject.toml
requirements.txt
setup.cfg
setup.py
tox.ini
.github/scripts/increment-tag.sh
.github/workflows/master.yml
.github/workflows/release_to_pypi.yml
ansiblelint_custom_rules_zjleblanc.egg-info/PKG-INFO
ansiblelint_custom_rules_zjleblanc.egg-info/SOURCES.txt
ansiblelint_custom_rules_zjleblanc.egg-info/dependency_links.txt
ansiblelint_custom_rules_zjleblanc.egg-info/requires.txt
ansiblelint_custom_rules_zjleblanc.egg-info/top_level.txt
rules/__init__.py
rules/_version.py
rules/task_module_last.py
rules/when_follows_name.py
tests/__init__.py
tests/requirements.txt
tests/task_module_last_tests.py
tests/when_follows_name_tests.py
tests/playbooks/task-module-last/fail.yml
tests/playbooks/task-module-last/success.yml
tests/playbooks/when-follows-name/fail.yml
tests/playbooks/when-follows-name/success.yml